wotw_highlighter/VERSION
wotw_highlighter/__init__.py
wotw_highlighter/__version__.py
wotw_highlighter/block.py
wotw_highlighter/block_decorator.py
wotw_highlighter/block_header.py
wotw_highlighter/block_highlighter.py
wotw_highlighter/block_loader.py
wotw_highlighter/block_options.py
wotw_highlighter/block_styler.py
wotw_highlighter/data/pygments-monokai-additions.css
wotw_highlighter/data/pygments-monokai.css
wotw_highlighter-0.3.0.dist-info/DESCRIPTION.rst
wotw_highlighter-0.3.0.dist-info/METADATA
wotw_highlighter-0.3.0.dist-info/RECORD
wotw_highlighter-0.3.0.dist-info/WHEEL
wotw_highlighter-0.3.0.dist-info/metadata.json
wotw_highlighter-0.3.0.dist-info/scratch.py
wotw_highlighter-0.3.0.dist-info/top_level.txt
