Metadata-Version: 2.0
Name: wotw-highlighter
Version: 0.3.0
Summary: Formats code as an editor-esque (Sublime, VS Code) block
Home-page: https://github.com/wizardsoftheweb/wotw-highlighter#readme
Author: CJ Harries
Author-email: cj@wizardsoftheweb.pro
License: ISC
Platform: UNKNOWN
Requires-Dist: premailer
Requires-Dist: pygments
Requires-Dist: pytest-runner
